quantr/__init__.py
quantr-0.1.1.dist-info/LICENSE
quantr-0.1.1.dist-info/METADATA
quantr-0.1.1.dist-info/WHEEL
quantr-0.1.1.dist-info/top_level.txt
quantr-0.1.1.dist-info/RECORD
